flake8_qchecker/__init__.py
flake8_qchecker-1.0.0a1.dist-info/METADATA
flake8_qchecker-1.0.0a1.dist-info/WHEEL
flake8_qchecker-1.0.0a1.dist-info/entry_points.txt
flake8_qchecker-1.0.0a1.dist-info/top_level.txt
flake8_qchecker-1.0.0a1.dist-info/RECORD
