Metadata-Version: 2.1
Name: flake8-qchecker
Version: 1.0.0a1
Summary: Flake8 plugin for qChecker
Home-page: https://github.com/James-Ansley/flake8-qchecker
Author: James Finnie-Ansley
License: MIT License
Keywords: flake8
Classifier: Development Status :: 1 - Planning
Classifier: Environment :: Console
Classifier: Intended Audience :: Developers
Classifier: Natural Language :: English
Classifier: Operating System :: OS Independent
Classifier: Programming Language :: Python :: 3
Classifier: Programming Language :: Python :: 3.10
Classifier: Topic :: Software Development
Classifier: Framework :: Flake8
Requires-Python: >=3.10
Requires-Dist: flake8 (>=4.0.1)
Requires-Dist: qchecker (~=1.1.0)
